rivr_rest/__init__.py
rivr_rest/resource.py
rivr_rest/router.py
rivr_rest/deserialization/__init__.py
rivr_rest/deserialization/hal.py
rivr_rest/deserialization/json.py
rivr_rest/deserialization/utils.py
rivr_rest/tests/__init__.py
rivr_rest/tests/test_resource.py
rivr_rest/tests/test_router.py
rivr_rest/tests/deserialization/__init__.py
rivr_rest/tests/deserialization/resources.py
rivr_rest/tests/deserialization/test_hal.py
rivr_rest/tests/deserialization/test_json.py
rivr_rest-0.1.0.dist-info/DESCRIPTION.rst
rivr_rest-0.1.0.dist-info/METADATA
rivr_rest-0.1.0.dist-info/metadata.json
rivr_rest-0.1.0.dist-info/RECORD
rivr_rest-0.1.0.dist-info/top_level.txt
rivr_rest-0.1.0.dist-info/WHEEL
