Metadata-Version: 2.0
Name: rivr-rest
Version: 0.1.0
Summary: Library for building REST apis.
Home-page: https://github.com/rivrproject/rivr-rest
Author: Kyle Fuller
Author-email: inbox@kylefuller.co.uk
License: BSD
Platform: UNKNOWN
Classifier: Programming Language :: Python :: 2
Classifier: Programming Language :: Python :: 2.7
Classifier: Programming Language :: Python :: 3
Classifier: Programming Language :: Python :: 3.2
Classifier: Programming Language :: Python :: 3.3
Classifier: Programming Language :: Python :: 3.4
Classifier: License :: OSI Approved :: BSD License
Requires-Dist: rivr
Requires-Dist: uritemplate
Requires-Dist: negotiator
